energex/__init__.py
energex/data_fetcher.py
energex/database.py
energex/main.py
energex/analysis/futures.py
energex/analysis/quality.py
energex/analysis/volatility.py
energex/visualization/charts.py
energex-0.2.0.dist-info/METADATA
energex-0.2.0.dist-info/WHEEL
energex-0.2.0.dist-info/licenses/LICENSE
energex-0.2.0.dist-info/RECORD
