Metadata-Version: 2.4
Name: energex
Version: 0.2.0
Summary: Energy derivatives data collection and analysis system
Author-email: Marty H <oldhero5@proton.me>
License: MIT
License-File: LICENSE
Classifier: Development Status :: 4 - Beta
Classifier: Intended Audience :: Financial and Insurance Industry
Classifier: License :: OSI Approved :: MIT License
Classifier: Programming Language :: Python :: 3.10
Classifier: Topic :: Office/Business :: Financial :: Investment
Requires-Python: >=3.10
Requires-Dist: duckdb>=0.9.0
Requires-Dist: numpy>=1.24.0
Requires-Dist: plotly>=5.18.0
Requires-Dist: polars>=0.20.0
Requires-Dist: pytz>=2024.1
Requires-Dist: yfinance>=0.2.35
Provides-Extra: dev
Requires-Dist: black>=23.0.0; extra == 'dev'
Requires-Dist: isort>=5.0.0; extra == 'dev'
Requires-Dist: mypy>=1.0.0; extra == 'dev'
Requires-Dist: pytest>=7.0.0; extra == 'dev'
